commandalarm/__init__.py
commandalarm/commandalarm.py
CommandAlarm-0.2.8.dist-info/LICENSE
CommandAlarm-0.2.8.dist-info/METADATA
CommandAlarm-0.2.8.dist-info/WHEEL
CommandAlarm-0.2.8.dist-info/entry_points.txt
CommandAlarm-0.2.8.dist-info/top_level.txt
CommandAlarm-0.2.8.dist-info/RECORD
