Metadata-Version: 2.1
Name: CommandAlarm
Version: 0.2.8
Summary: A simple command line program that allows users to set an alarm with a custom command.
Home-page: https://github.com/alofgren/commandalarm
Author: alofgren
Author-email: drelofren@outlook.com
License: GPLv3+
Project-URL: Source, https://github.com/alofgren/commandalarm
Project-URL: Bug Reports, https://github.com/alofgren/commandalarm/issues
Project-URL: Changelog, https://github.com/alofgren/commandalarm/blob/main/CHANGELOG.md
Keywords: alarm,command,command-line,tool,timer,commandalarm
Classifier: Development Status :: 3 - Alpha
Classifier: Environment :: Console
Classifier: Intended Audience :: End Users/Desktop
Classifier: License :: OSI Approved :: GNU General Public License v3 or later (GPLv3+)
Classifier: Natural Language :: English
Classifier: Operating System :: OS Independent
Classifier: Programming Language :: Python :: 3
Classifier: Programming Language :: Python :: 3.7
Classifier: Programming Language :: Python :: 3.8
Classifier: Programming Language :: Python :: 3.9
Classifier: Programming Language :: Python :: 3.10
Classifier: Programming Language :: Python :: 3.11
Classifier: Programming Language :: Python :: 3.12
Classifier: Programming Language :: Python :: Implementation :: CPython
Classifier: Topic :: Utilities
Requires-Python: >=3.7
License-File: LICENSE
